vim_vroom-0.14.0.data/scripts/respond.vroomfaker
vim_vroom-0.14.0.data/scripts/shell.vroomfaker
vim_vroom-0.14.0.data/scripts/vroom
vroom/__init__.py
vroom/__main__.py
vroom/actions.py
vroom/args.py
vroom/buffer.py
vroom/color.py
vroom/command.py
vroom/controls.py
vroom/environment.py
vroom/messages.py
vroom/neovim_mod.py
vroom/output.py
vroom/result.py
vroom/runner.py
vroom/shell.py
vroom/test.py
vroom/vim.py
vim_vroom-0.14.0.dist-info/LICENSE
vim_vroom-0.14.0.dist-info/METADATA
vim_vroom-0.14.0.dist-info/WHEEL
vim_vroom-0.14.0.dist-info/top_level.txt
vim_vroom-0.14.0.dist-info/RECORD
