Metadata-Version: 2.1
Name: vim-vroom
Version: 0.14.0
Summary: Launch your vimscript tests
Author-email: Nate Soares <nate@so8r.es>
License: 
Project-URL: Repository, https://github.com/google/vroom
Classifier: Development Status :: 3 - Alpha
Classifier: License :: OSI Approved :: Apache Software License
Classifier: Programming Language :: Python :: 3
Classifier: Programming Language :: Python :: 3.4
Classifier: Topic :: Software Development :: Testing
Requires-Python: >=3.4
License-File: LICENSE
